[{"Date":"2024-08-10T12:24:08.000Z","Article sentiment":"Nan too long","Article title":null,"link":null,"publisher":null},{"Date":"2024-08-08T21:51:45.000Z","Article sentiment":"Nan too long","Article title":null,"link":null,"publisher":null},{"Date":"None","Article sentiment":"neutral","Article title":"Acacia Research Reports Second Quarter 2024 Financial Results","link":"https:\/\/finance.yahoo.com\/news\/acacia-research-reports-second-quarter-200500263.html","publisher":"Business Wire"},{"Date":"None","Article sentiment":"neutral","Article title":"Acacia Research to Release Second Quarter 2024 Financial Results on August 8","link":"https:\/\/finance.yahoo.com\/news\/acacia-research-release-second-quarter-113000458.html","publisher":"Business Wire"},{"Date":"None","Article sentiment":"neutral","Article title":"7 Small-Cap Stocks With Massive Potential Returns","link":"https:\/\/finance.yahoo.com\/news\/7-small-cap-stocks-massive-110000860.html","publisher":"InvestorPlace"},{"Date":"None","Article sentiment":"neutral","Article title":"Treasure Hunt: 7 Penny Stocks Wall Street Hasn\u2019t Discovered Yet","link":"https:\/\/finance.yahoo.com\/news\/treasure-hunt-7-penny-stocks-100900697.html","publisher":"InvestorPlace"},{"Date":"None","Article sentiment":"neutral","Article title":"3 Undiscovered Stocks Set to Double Your Money","link":"https:\/\/finance.yahoo.com\/news\/3-undiscovered-stocks-set-double-103000221.html","publisher":"InvestorPlace"},{"Date":"None","Article sentiment":"neutral","Article title":"Have $5-10? 7 Affordable Stocks That Are About to Breakout.","link":"https:\/\/finance.yahoo.com\/news\/5-10-7-affordable-stocks-100000649.html","publisher":"InvestorPlace"}]