[{"Date":"2024-05-13T21:32:10.000Z","Article title":"Terran Orbital Selected by Lockheed Martin to Produce 18 Satellite Buses for Space Development Agency","link":"https:\/\/finance.yahoo.com\/news\/terran-orbital-selected-lockheed-martin-213210084.html","publisher":"MT Newswires","Article sentiment":"neutral"},{"Date":"2024-05-13T19:50:08.000Z","Article title":null,"link":null,"publisher":null,"Article sentiment":"Nan too long"},{"Date":"2024-05-13T17:28:00.000Z","Article title":"Citi Says Defense Sector Better Than It Seems. 2 Stocks to Buy.","link":"https:\/\/finance.yahoo.com\/m\/3c4c27db-c74f-379c-9bab-0f8ebcee85b6\/citi-says-defense-sector.html","publisher":"Barrons.com","Article sentiment":"positive"},{"Date":"2024-05-13T14:27:52.000Z","Article title":null,"link":null,"publisher":null,"Article sentiment":"Nan too long"},{"Date":"2024-05-12T11:00:23.000Z","Article title":null,"link":null,"publisher":null,"Article sentiment":"Nan too long"},{"Date":"2024-05-10T13:00:11.000Z","Article title":null,"link":null,"publisher":null,"Article sentiment":"Nan too long"},{"Date":"2024-05-10T03:38:18.000Z","Article title":null,"link":null,"publisher":null,"Article sentiment":"Nan too long"},{"Date":"2024-05-09T23:17:14.000Z","Article title":null,"link":null,"publisher":null,"Article sentiment":"Nan too long"}]